<settings>
    <database>
        <system>hbase-phoenix</system>
        <connection>
            jdbc:phoenix:narcana-hbase01.statsbiblioteket.dk,narcana-hbase02.statsbiblioteket.dk,narcana-yarn01.statsbiblioteket.dk,narcana-yarn02.statsbiblioteket.dk,narcana-ambari01.statsbiblioteket.dk:2181:/hbase
        </connection>
    </database>
    <env>prod</env>
    <mail>
        <host>localhost</host>
        <admin>webdanica@localhost</admin>
        <port>25</port>
    </mail>
    <harvesting>
        <maxSingleSeedHarvests>10</maxSingleSeedHarvests>
        <schedule>Once</schedule>
        <template>webdanica_order</template>
        <prefix>webdanica-trial-</prefix>
        <maxbytes>10000000</maxbytes>
        <maxobjects>100</maxobjects>
        <harvestlogDir>/opt/webdanica/harvestlogs/</harvestlogDir>
        <harvestMaxTimeInMillis>900000</harvestMaxTimeInMillis>
    </harvesting>
    <seeds>
        <rejectDkUrls>true</rejectDkUrls>
        <ignoredSuffixes>
            <suffix>.0xe</suffix>
            <suffix>.73k</suffix>
            <suffix>.7z</suffix>
            <suffix>.89k</suffix>
            <suffix>.a6p</suffix>
            <suffix>.aac</suffix>
            <suffix>.ac</suffix>
            <suffix>.acc</suffix>
            <suffix>.accde</suffix>
            <suffix>.acr</suffix>
            <suffix>.action</suffix>
            <suffix>.actm</suffix>
            <suffix>.ahk</suffix>
            <suffix>.air</suffix>
            <suffix>.apk</suffix>
            <suffix>.app</suffix>
            <suffix>.arscript</suffix>
            <suffix>.as</suffix>
            <suffix>.asb</suffix>
            <suffix>.avi</suffix>
            <suffix>.awk</suffix>
            <suffix>.azw2</suffix>
            <suffix>.bat</suffix>
            <suffix>.beam</suffix>
            <suffix>.bin</suffix>
            <suffix>.bmp</suffix>
            <suffix>.btm</suffix>
            <suffix>.cel</suffix>
            <suffix>.celx</suffix>
            <suffix>.chm</suffix>
            <suffix>.class</suffix>
            <suffix>.cmd</suffix>
            <suffix>.cof</suffix>
            <suffix>.com</suffix>
            <suffix>.command</suffix>
            <suffix>.cpl</suffix>
            <suffix>.crt</suffix>
            <suffix>.csh</suffix>
            <suffix>.css</suffix>
            <suffix>.dek</suffix>
            <suffix>.dld</suffix>
            <suffix>.dll</suffix>
            <suffix>.dmc</suffix>
            <suffix>.doc</suffix>
            <suffix>.docm</suffix>
            <suffix>.docx</suffix>
            <suffix>.dot</suffix>
            <suffix>.dotm</suffix>
            <suffix>.dxl</suffix>
            <suffix>.ear</suffix>
            <suffix>.ebm</suffix>
            <suffix>.ebs</suffix>
            <suffix>.ebs2</suffix>
            <suffix>.ecf</suffix>
            <suffix>.eham</suffix>
            <suffix>.elf</suffix>
            <suffix>.eps</suffix>
            <suffix>.es</suffix>
            <suffix>.ex4</suffix>
            <suffix>.exe</suffix>
            <suffix>.exopc</suffix>
            <suffix>.ezs</suffix>
            <suffix>.fas</suffix>
            <suffix>.fky</suffix>
            <suffix>.flac</suffix>
            <suffix>.fpi</suffix>
            <suffix>.frm</suffix>
            <suffix>.frs</suffix>
            <suffix>.fxp</suffix>
            <suffix>.gadget</suffix>
            <suffix>.gif</suffix>
            <suffix>.gs</suffix>
            <suffix>.ham</suffix>
            <suffix>.hms</suffix>
            <suffix>.hpf</suffix>
            <suffix>.hta</suffix>
            <suffix>.ico</suffix>
            <suffix>.iim</suffix>
            <suffix>.inf1</suffix>
            <suffix>.ins</suffix>
            <suffix>.inx</suffix>
            <suffix>.ipa</suffix>
            <suffix>.ipf</suffix>
            <suffix>.iso</suffix>
            <suffix>.isp</suffix>
            <suffix>.isu</suffix>
            <suffix>.jar</suffix>
            <suffix>.job</suffix>
            <suffix>.jp2</suffix>
            <suffix>.jpe</suffix>
            <suffix>.jpeg</suffix>
            <suffix>.jpg</suffix>
            <suffix>.js</suffix>
            <suffix>.jse</suffix>
            <suffix>.jsx</suffix>
            <suffix>.kix</suffix>
            <suffix>.ksh</suffix>
            <suffix>.lnk</suffix>
            <suffix>.lo</suffix>
            <suffix>.ls</suffix>
            <suffix>.mam</suffix>
            <suffix>.mcr</suffix>
            <suffix>.mdb</suffix>
            <suffix>.mel</suffix>
            <suffix>.mka</suffix>
            <suffix>.mkv</suffix>
            <suffix>.mov</suffix>
            <suffix>.mp3</suffix>
            <suffix>.mp4</suffix>
            <suffix>.mpeg</suffix>
            <suffix>.mpg</suffix>
            <suffix>.mpx</suffix>
            <suffix>.mrc</suffix>
            <suffix>.ms</suffix>
            <suffix>.msc</suffix>
            <suffix>.msi</suffix>
            <suffix>.msp</suffix>
            <suffix>.mst</suffix>
            <suffix>.mxe</suffix>
            <suffix>.nexe</suffix>
            <suffix>.obs</suffix>
            <suffix>.odt</suffix>
            <suffix>.ogg</suffix>
            <suffix>.ore</suffix>
            <suffix>.osx</suffix>
            <suffix>.otm</suffix>
            <suffix>.out</suffix>
            <suffix>.paf</suffix>
            <suffix>.pdd</suffix>
            <suffix>.pdf</suffix>
            <suffix>.pex</suffix>
            <suffix>.pict</suffix>
            <suffix>.pif</suffix>
            <suffix>.plx</suffix>
            <suffix>.png</suffix>
            <suffix>.potm</suffix>
            <suffix>.ppam</suffix>
            <suffix>.ppsm</suffix>
            <suffix>.pptm</suffix>
            <suffix>.prc</suffix>
            <suffix>.prg</suffix>
            <suffix>.ps1</suffix>
            <suffix>.psd</suffix>
            <suffix>.pvd</suffix>
            <suffix>.pwc</suffix>
            <suffix>.pyc</suffix>
            <suffix>.pyo</suffix>
            <suffix>.qpx</suffix>
            <suffix>.rar</suffix>
            <suffix>.raw</suffix>
            <suffix>.rbx</suffix>
            <suffix>.reg</suffix>
            <suffix>.rgs</suffix>
            <suffix>.rox</suffix>
            <suffix>.rpj</suffix>
            <suffix>.rtf</suffix>
            <suffix>.run</suffix>
            <suffix>.s2a</suffix>
            <suffix>.sbs</suffix>
            <suffix>.sca</suffix>
            <suffix>.scar</suffix>
            <suffix>.scb</suffix>
            <suffix>.scr</suffix>
            <suffix>.script</suffix>
            <suffix>.sct</suffix>
            <suffix>.shb</suffix>
            <suffix>.shs</suffix>
            <suffix>.smm</suffix>
            <suffix>.so</suffix>
            <suffix>.spr</suffix>
            <suffix>.sqlite</suffix>
            <suffix>.swf</suffix>
            <suffix>.tar</suffix>
            <suffix>.tcp</suffix>
            <suffix>.thm</suffix>
            <suffix>.tif</suffix>
            <suffix>.tiff</suffix>
            <suffix>.tlb</suffix>
            <suffix>.tms</suffix>
            <suffix>.u3p</suffix>
            <suffix>.udf</suffix>
            <suffix>.upx</suffix>
            <suffix>.url</suffix>
            <suffix>.vb</suffix>
            <suffix>.vbe</suffix>
            <suffix>.vbs</suffix>
            <suffix>.vbscript</suffix>
            <suffix>.vlx</suffix>
            <suffix>.vob</suffix>
            <suffix>.vpm</suffix>
            <suffix>.wav</suffix>
            <suffix>.waw</suffix>
            <suffix>.wcm</suffix>
            <suffix>.widget</suffix>
            <suffix>.wiz</suffix>
            <suffix>.wma</suffix>
            <suffix>.workflow</suffix>
            <suffix>.wpk</suffix>
            <suffix>.wpm</suffix>
            <suffix>.wps</suffix>
            <suffix>.ws</suffix>
            <suffix>.wsf</suffix>
            <suffix>.wsf</suffix>
            <suffix>.wsh</suffix>
            <suffix>.xap</suffix>
            <suffix>.xbap</suffix>
            <suffix>.xlam</suffix>
            <suffix>.xlm</suffix>
            <suffix>.xls</suffix>
            <suffix>.xlsm</suffix>
            <suffix>.xltm</suffix>
            <suffix>.xqt</suffix>
            <suffix>.xys</suffix>
            <suffix>.zip</suffix>
            <suffix>.zl9</suffix>
        </ignoredSuffixes>
        <acceptedProtocols>
            <protocol>http</protocol>
            <protocol>https</protocol>
        </acceptedProtocols>
    </seeds>
    <webapp>
        <filtering>
            <maxRecordsProcessedPerRun>50000</maxRecordsProcessedPerRun>
        </filtering>
        <crontab>
            <filtering>*/9 * * * *</filtering>
            <harvesting>*/9 * * * *</harvesting>
            <statecaching>0,15,30,45 * * * *</statecaching>
        </crontab>

        <resources>
            <defaultsecuredsetting>false</defaultsecuredsetting>
            <resource>
                <path>/harvests/</path>
                <secured>false</secured>
            </resource>

            <resource>
                <path>/harvest/</path>
                <secured>false</secured>
            </resource>

            <resource>
                <path>/domains/</path>
                <secured>false</secured>
            </resource>

            <resource>
                <path>/domain/</path>
                <secured>false</secured>
            </resource>

            <resource>
                <path>/blacklists/</path>
                <secured>false</secured>
            </resource>

            <resource>
                <path>/blacklist/</path>
                <secured>false</secured>
            </resource>

            <resource>
                <path>/status/</path>
                <secured>false</secured>
            </resource>

            <resource>
                <path>/status/props/</path>
                <secured>false</secured>
            </resource>

            <resource>
                <path>/status/dep/</path>
                <secured>false</secured>
            </resource>

            <resource>
                <path>/status/threads/</path>
                <secured>false</secured>
            </resource>

            <resource>
                <path>/status/progress/</path>
                <secured>false</secured>
            </resource>

            <resource>
                <path>/status/log/</path>
                <secured>false</secured>
            </resource>

            <resource>
                <path>/status/healthy/</path>
                <secured>true</secured>
            </resource>
            <resource>
                <path>/status/sqlquery/</path>
                <secured>true</secured>
            </resource>
            <resource>
                <path>/criteriaresult/</path>
                <secured>true</secured>
            </resource>
            <resource>
                <path>/criteriaresults/</path>
                <secured>true</secured>
            </resource>

            <resource>
                <path>/ingestlogs/</path>
                <secured>false</secured>
            </resource>

            <resource>
                <path>/ingestlog/</path>
                <secured>false</secured>
            </resource>

            <resource>
                <path>/img/*</path>
                <secured>false</secured>
            </resource>

            <resource>
                <path>/js/*</path>
                <secured>false</secured>
            </resource>

            <resource>
                <path>/</path>
                <secured>false</secured>
            </resource>

            <resource>
                <path>/seed/</path>
                <secured>false</secured>
            </resource>


            <resource>
                <path>/seeds/</path>
                <secured>false</secured>
            </resource>
            <!-- %3C%3E = <> %3C%3E -->
            <resource>
                <path>/seeds/%3Cnumeric%3E/</path>
                <secured>false</secured>
            </resource>

            <resource>
                <path>/seeds/%3Cnumeric%3E/dump/</path>
                <secured>false</secured>
            </resource>

        </resources>
    </webapp>
</settings>
